bb2_cyanide_api/__init__.py
bb2_cyanide_api/adapter.py
bb2_cyanide_api/api.py
bb2_cyanide_api/match.py
bb2_cyanide_api/tournament.py
bb2_cyanide_api-0.0.6.dist-info/LICENSE
bb2_cyanide_api-0.0.6.dist-info/METADATA
bb2_cyanide_api-0.0.6.dist-info/WHEEL
bb2_cyanide_api-0.0.6.dist-info/top_level.txt
bb2_cyanide_api-0.0.6.dist-info/RECORD
