Metadata-Version: 2.1
Name: bb2-cyanide-api
Version: 0.0.6
Summary: Cyanide BB2 API wrapper
Home-page: https://github.com/ttrnecka/bb2_cyanide_api
Author: Tomas Trnecka
Author-email: trnecka@gmail.com
License: UNKNOWN
Platform: UNKNOWN
Classifier: Programming Language :: Python :: 3
Classifier: License :: OSI Approved :: MIT License
Classifier: Operating System :: OS Independent
Requires-Python: >=3.6
